{
    "product": {
        "badges": {
            "is_water": {
                "value": false,
                "previous": [],
                "timestamp": 1742983404
            },
            "requires_age_check": {
                "value": false,
                "previous": [],
                "timestamp": 1742983404
            }
        },
        "categories": [
            {
                "id": {
                    "value": 17,
                    "previous": [],
                    "timestamp": 1742983404
                },
                "name": {
                    "value": "Congelados",
                    "previous": [],
                    "timestamp": 1742983404
                },
                "level": {
                    "value": 0,
                    "previous": [],
                    "timestamp": 1742983404
                },
                "order": {
                    "value": 213,
                    "previous": [],
                    "timestamp": 1742983404
                }
            }
        ],
        "display_name": {
            "value": "Hielo cocktail",
            "previous": [],
            "timestamp": 1742983404
        },
        "id": {
            "value": "64139",
            "previous": [],
            "timestamp": 1742983404
        },
        "limit": {
            "value": 999,
            "previous": [],
            "timestamp": 1742983404
        },
        "packaging": {
            "value": "Paquete",
            "previous": [],
            "timestamp": 1742983404
        },
        "price_instructions": {
            "iva": {
                "value": 10,
                "previous": [],
                "timestamp": 1742983404
            },
            "is_new": {
                "value": false,
                "previous": [],
                "timestamp": 1742983404
            },
            "is_pack": {
                "value": false,
                "previous": [],
                "timestamp": 1742983404
            },
            "pack_size": {
                "value": null,
                "previous": [],
                "timestamp": 1742983404
            },
            "unit_name": {
                "value": null,
                "previous": [],
                "timestamp": 1742983404
            },
            "unit_size": {
                "value": 2,
                "previous": [],
                "timestamp": 1742983404
            },
            "bulk_price": {
                "value": "0.65",
                "previous": [],
                "timestamp": 1742983404
            },
            "unit_price": {
                "value": "1.30",
                "previous": [],
                "timestamp": 1742983404
            },
            "approx_size": {
                "value": false,
                "previous": [],
                "timestamp": 1742983404
            },
            "size_format": {
                "value": "kg",
                "previous": [],
                "timestamp": 1742983404
            },
            "total_units": {
                "value": null,
                "previous": [],
                "timestamp": 1742983404
            },
            "unit_selector": {
                "value": true,
                "previous": [],
                "timestamp": 1742983404
            },
            "bunch_selector": {
                "value": false,
                "previous": [],
                "timestamp": 1742983404
            },
            "drained_weight": {
                "value": null,
                "previous": [],
                "timestamp": 1742983404
            },
            "selling_method": {
                "value": 0,
                "previous": [],
                "timestamp": 1742983404
            },
            "tax_percentage": {
                "value": "10.000",
                "previous": [],
                "timestamp": 1742983404
            },
            "price_decreased": {
                "value": false,
                "previous": [],
                "timestamp": 1742983404
            },
            "reference_price": {
                "value": "0.650",
                "previous": [],
                "timestamp": 1742983404
            },
            "min_bunch_amount": {
                "value": 1,
                "previous": [],
                "timestamp": 1742983404
            },
            "reference_format": {
                "value": "kg",
                "previous": [],
                "timestamp": 1742983404
            },
            "previous_unit_price": {
                "value": null,
                "previous": [],
                "timestamp": 1742983404
            },
            "increment_bunch_amount": {
                "value": 1,
                "previous": [],
                "timestamp": 1742983404
            }
        },
        "published": {
            "value": true,
            "previous": [],
            "timestamp": 1742983404
        },
        "share_url": {
            "value": "https:\/\/tienda.mercadona.es\/product\/64139\/hielo-cocktail-paquete",
            "previous": [],
            "timestamp": 1742983404
        },
        "slug": {
            "value": "hielo-cocktail-paquete",
            "previous": [],
            "timestamp": 1742983404
        },
        "status": {
            "value": null,
            "previous": [],
            "timestamp": 1742983404
        },
        "thumbnail": {
            "value": "https:\/\/prod-mercadona.imgix.net\/images\/58a58d2dac231f62b518bdb84368e9fd.jpg?fit=crop&h=300&w=300",
            "previous": [],
            "timestamp": 1742983404
        },
        "unavailable_from": {
            "value": null,
            "previous": [],
            "timestamp": 1742983404
        }
    },
    "stats": {
        "created_at": 1742983404,
        "updated_at": 1749739150,
        "updates": 3
    }
}